attributedict/__init__.py
attributedict/__init__.pyc
attributedict/collections.py
attributedict/collections.pyc
attributedict/compat.py
attributedict/compat.pyc
attributedict/tests/__init__.py
attributedict/tests/__main__.py
attributedict/tests/helper.py
attributedict/tests/test_collections.py
attributedict-0.3.0.dist-info/METADATA
attributedict-0.3.0.dist-info/WHEEL
attributedict-0.3.0.dist-info/top_level.txt
attributedict-0.3.0.dist-info/zip-safe
attributedict-0.3.0.dist-info/RECORD
