Metadata-Version: 2.1
Name: attributedict
Version: 0.3.0
Summary: A dictionary object with attributes support.
Home-page: https://github.com/grimen/python-attributedict
Author: Jonas Grimfelt
Author-email: grimen@gmail.com
License: MIT
Download-URL: https://github.com/grimen/python-attributedict
Project-URL: repository, https://github.com/grimen/python-attributedict
Project-URL: bugs, https://github.com/grimen/python-attributedict/issues
Keywords: object,dict,dictionary,collection,attributes,attribute,attr,properties,property,props,openstruct,struct,hashmap
Platform: UNKNOWN
Classifier: Topic :: Software Development :: Libraries
Classifier: Development Status :: 5 - Production/Stable
Classifier: Intended Audience :: Developers
Classifier: License :: OSI Approved :: MIT License
Classifier: Operating System :: POSIX
Classifier: Programming Language :: Python
Classifier: Programming Language :: Python :: 2
Classifier: Programming Language :: Python :: 2.7
Classifier: Programming Language :: Python :: 3
Classifier: Programming Language :: Python :: 3.6
Classifier: Programming Language :: Python :: Implementation :: CPython
Classifier: Programming Language :: Python :: Implementation :: PyPy
